[
    {
        "id": 8,
        "name": "Saving Product 01",
        "shortName": "SP01",
        "description": "General Savings Productv",
        "currency": {
            "code": "VND",
            "name": "Vietnamese Dong",
            "decimalPlaces": 2,
            "inMultiplesOf": 0,
            "nameCode": "currency.VND",
            "displayLabel": "Vietnamese Dong [VND]"
        },
        "nominalAnnualInterestRate": 2.500000,
        "interestCompoundingPeriodType": {
            "id": 1,
            "code": "savings.interest.period.savingsCompoundingInterestPeriodType.daily",
            "value": "Daily"
        },
        "interestPostingPeriodType": {
            "id": 4,
            "code": "savings.interest.posting.period.savingsPostingInterestPeriodType.monthly",
            "value": "Monthly"
        },
        "interestCalculationType": {
            "id": 2,
            "code": "savingsInterestCalculationType.averagedailybalance",
            "value": "Average Daily Balance"
        },
        "interestCalculationDaysInYearType": {
            "id": 365,
            "code": "savingsInterestCalculationDaysInYearType.days365",
            "value": "365 Days"
        },
        "minRequiredOpeningBalance": 20.000000,
        "lockinPeriodFrequency": 3,
        "lockinPeriodFrequencyType": {
            "id": 2,
            "code": "savings.lockin.savingsPeriodFrequencyType.months",
            "value": "Months"
        },
        "withdrawalFeeForTransfers": false,
        "allowOverdraft": true,
        "overdraftLimit": 0.000000,
        "minRequiredBalance": 1.000000,
        "enforceMinRequiredBalance": true,
        "minBalanceForInterestCalculation": 1.000000,
        "nominalAnnualInterestRateOverdraft": 0.000000,
        "minOverdraftForInterestCalculation": 0.000000,
        "withHoldTax": true,
        "taxGroup": {
            "id": 1,
            "name": "taxGrp"
        },
        "accountingRule": {
            "id": 1,
            "code": "accountingRuleType.none",
            "value": "NONE"
        },
        "isDormancyTrackingActive": true,
        "daysToInactive": 90,
        "daysToDormancy": 180,
        "daysToEscheat": 3650
    },
    {
        "id": 9,
        "name": "Testing123",
        "shortName": "Test",
        "currency": {
            "code": "ALL",
            "name": "Albanian Lek",
            "decimalPlaces": 2,
            "inMultiplesOf": 0,
            "nameCode": "currency.ALL",
            "displayLabel": "Albanian Lek [ALL]"
        },
        "nominalAnnualInterestRate": 3.000000,
        "interestCompoundingPeriodType": {
            "id": 1,
            "code": "savings.interest.period.savingsCompoundingInterestPeriodType.daily",
            "value": "Daily"
        },
        "interestPostingPeriodType": {
            "id": 4,
            "code": "savings.interest.posting.period.savingsPostingInterestPeriodType.monthly",
            "value": "Monthly"
        },
        "interestCalculationType": {
            "id": 1,
            "code": "savingsInterestCalculationType.dailybalance",
            "value": "Daily Balance"
        },
        "interestCalculationDaysInYearType": {
            "id": 365,
            "code": "savingsInterestCalculationDaysInYearType.days365",
            "value": "365 Days"
        },
        "withdrawalFeeForTransfers": true,
        "allowOverdraft": false,
        "overdraftLimit": 0.000000,
        "minRequiredBalance": 0.000000,
        "enforceMinRequiredBalance": true,
        "nominalAnnualInterestRateOverdraft": 0.000000,
        "minOverdraftForInterestCalculation": 0.000000,
        "withHoldTax": true,
        "taxGroup": {
            "id": 1,
            "name": "taxGrp"
        },
        "accountingRule": {
            "id": 1,
            "code": "accountingRuleType.none",
            "value": "NONE"
        },
        "isDormancyTrackingActive": false
    },
    {
        "id": 13,
        "name": "Default",
        "shortName": "DP",
        "description": "Default",
        "currency": {
            "code": "NGN",
            "name": "Nigerian Naira",
            "decimalPlaces": 2,
            "inMultiplesOf": 0,
            "nameCode": "currency.NGN",
            "displayLabel": "Nigerian Naira [NGN]"
        },
        "nominalAnnualInterestRate": 0.000000,
        "interestCompoundingPeriodType": {
            "id": 1,
            "code": "savings.interest.period.savingsCompoundingInterestPeriodType.daily",
            "value": "Daily"
        },
        "interestPostingPeriodType": {
            "id": 4,
            "code": "savings.interest.posting.period.savingsPostingInterestPeriodType.monthly",
            "value": "Monthly"
        },
        "interestCalculationType": {
            "id": 1,
            "code": "savingsInterestCalculationType.dailybalance",
            "value": "Daily Balance"
        },
        "interestCalculationDaysInYearType": {
            "id": 365,
            "code": "savingsInterestCalculationDaysInYearType.days365",
            "value": "365 Days"
        },
        "withdrawalFeeForTransfers": false,
        "allowOverdraft": false,
        "enforceMinRequiredBalance": false,
        "withHoldTax": true,
        "taxGroup": {
            "id": 1,
            "name": "taxGrp"
        },
        "accountingRule": {
            "id": 2,
            "code": "accountingRuleType.cash",
            "value": "CASH BASED"
        },
        "isDormancyTrackingActive": false
    },
    {
        "id": 35,
        "name": "Preneurolde",
        "shortName": "PO",
        "description": "tes",
        "currency": {
            "code": "IDR",
            "name": "Indonesian Rupiah",
            "decimalPlaces": 2,
            "inMultiplesOf": 100,
            "nameCode": "currency.IDR",
            "displayLabel": "Indonesian Rupiah [IDR]"
        },
        "nominalAnnualInterestRate": 6.000000,
        "interestCompoundingPeriodType": {
            "id": 4,
            "code": "savings.interest.period.savingsCompoundingInterestPeriodType.monthly",
            "value": "Monthly"
        },
        "interestPostingPeriodType": {
            "id": 4,
            "code": "savings.interest.posting.period.savingsPostingInterestPeriodType.monthly",
            "value": "Monthly"
        },
        "interestCalculationType": {
            "id": 1,
            "code": "savingsInterestCalculationType.dailybalance",
            "value": "Daily Balance"
        },
        "interestCalculationDaysInYearType": {
            "id": 365,
            "code": "savingsInterestCalculationDaysInYearType.days365",
            "value": "365 Days"
        },
        "minRequiredOpeningBalance": 500000.000000,
        "lockinPeriodFrequency": 3,
        "lockinPeriodFrequencyType": {
            "id": 0,
            "code": "savings.lockin.savingsPeriodFrequencyType.days",
            "value": "Days"
        },
        "withdrawalFeeForTransfers": true,
        "allowOverdraft": false,
        "minRequiredBalance": 50000.000000,
        "enforceMinRequiredBalance": true,
        "minBalanceForInterestCalculation": 50000.000000,
        "withHoldTax": true,
        "taxGroup": {
            "id": 1,
            "name": "taxGrp"
        },
        "accountingRule": {
            "id": 2,
            "code": "accountingRuleType.cash",
            "value": "CASH BASED"
        },
        "isDormancyTrackingActive": true,
        "daysToInactive": 365,
        "daysToDormancy": 730,
        "daysToEscheat": 1000
    },
    {
        "id": 40,
        "name": "AffDaily",
        "shortName": "Dail",
        "description": "Current ",
        "currency": {
            "code": "GHC",
            "name": "Ghana Cedi",
            "decimalPlaces": 2,
            "inMultiplesOf": 1,
            "displaySymbol": "GHc",
            "nameCode": "currency.GHC",
            "displayLabel": "Ghana Cedi (GHc)"
        },
        "nominalAnnualInterestRate": 10.000000,
        "interestCompoundingPeriodType": {
            "id": 1,
            "code": "savings.interest.period.savingsCompoundingInterestPeriodType.daily",
            "value": "Daily"
        },
        "interestPostingPeriodType": {
            "id": 5,
            "code": "savings.interest.posting.period.savingsPostingInterestPeriodType.quarterly",
            "value": "Quarterly"
        },
        "interestCalculationType": {
            "id": 1,
            "code": "savingsInterestCalculationType.dailybalance",
            "value": "Daily Balance"
        },
        "interestCalculationDaysInYearType": {
            "id": 360,
            "code": "savingsInterestCalculationDaysInYearType.days360",
            "value": "360 Days"
        },
        "minRequiredOpeningBalance": 20.000000,
        "withdrawalFeeForTransfers": false,
        "allowOverdraft": false,
        "minRequiredBalance": 20.000000,
        "enforceMinRequiredBalance": true,
        "minBalanceForInterestCalculation": 20.000000,
        "withHoldTax": true,
        "taxGroup": {
            "id": 3,
            "name": "interestLoanTaxGroup"
        },
        "accountingRule": {
            "id": 2,
            "code": "accountingRuleType.cash",
            "value": "CASH BASED"
        },
        "isDormancyTrackingActive": true,
        "daysToInactive": 180,
        "daysToDormancy": 270,
        "daysToEscheat": 360
    },
    {
        "id": 18,
        "name": "Sample Savings",
        "shortName": "SS",
        "description": "ss",
        "currency": {
            "code": "USD",
            "name": "US Dollar",
            "decimalPlaces": 2,
            "inMultiplesOf": 1,
            "displaySymbol": "$",
            "nameCode": "currency.USD",
            "displayLabel": "US Dollar ($)"
        },
        "nominalAnnualInterestRate": 10.000000,
        "interestCompoundingPeriodType": {
            "id": 1,
            "code": "savings.interest.period.savingsCompoundingInterestPeriodType.daily",
            "value": "Daily"
        },
        "interestPostingPeriodType": {
            "id": 4,
            "code": "savings.interest.posting.period.savingsPostingInterestPeriodType.monthly",
            "value": "Monthly"
        },
        "interestCalculationType": {
            "id": 1,
            "code": "savingsInterestCalculationType.dailybalance",
            "value": "Daily Balance"
        },
        "interestCalculationDaysInYearType": {
            "id": 365,
            "code": "savingsInterestCalculationDaysInYearType.days365",
            "value": "365 Days"
        },
        "withdrawalFeeForTransfers": false,
        "allowOverdraft": false,
        "enforceMinRequiredBalance": false,
        "withHoldTax": true,
        "taxGroup": {
            "id": 4,
            "name": "Withold tax"
        },
        "accountingRule": {
            "id": 2,
            "code": "accountingRuleType.cash",
            "value": "CASH BASED"
        },
        "isDormancyTrackingActive": false
    }
]